Metadata-Version: 2.1
Name: saiive.chain
Version: 2.3.1.0
Summary: BigchainDB: The Blockchain Database
Home-page: https://github.com/BigchainDB/bigchaindb/
Author: BigchainDB Contributors
Author-email: devs@bigchaindb.com
License: Apache Software License 2.0
Platform: UNKNOWN
Classifier: Development Status :: 4 - Beta
Classifier: Intended Audience :: Developers
Classifier: Topic :: Database
Classifier: Topic :: Database :: Database Engines/Servers
Classifier: Topic :: Software Development
Classifier: Natural Language :: English
Classifier: License :: OSI Approved :: Apache Software License
Classifier: Programming Language :: Python :: 3 :: Only
Classifier: Programming Language :: Python :: 3.5
Classifier: Programming Language :: Python :: 3.6
Classifier: Operating System :: MacOS :: MacOS X
Classifier: Operating System :: POSIX :: Linux
Requires-Python: >=3.6
Requires-Dist: pymongo (~=3.6)
Requires-Dist: cryptoconditions (==0.8.0)
Requires-Dist: python-rapidjson (~=0.6.0)
Requires-Dist: logstats (~=0.2.1)
Requires-Dist: flask (==1.0.0)
Requires-Dist: flask-httpauth (==4.2.0)
Requires-Dist: flask-cors (~=3.0.0)
Requires-Dist: flask-restful (~=0.3.0)
Requires-Dist: requests (~=2.20.0)
Requires-Dist: gunicorn (~=19.9)
Requires-Dist: jsonschema (~=2.5.1)
Requires-Dist: pyyaml (>=4.2b1)
Requires-Dist: aiohttp (~=3.0)
Requires-Dist: bigchaindb-abci (>=1.0.2)
Requires-Dist: setproctitle (~=1.1.0)
Requires-Dist: packaging (~=18.0)
Requires-Dist: yarl (==1.4.2)
Requires-Dist: greenlet (==0.4.16)
Provides-Extra: dev
Requires-Dist: ipdb ; extra == 'dev'
Requires-Dist: ipython ; extra == 'dev'
Requires-Dist: watchdog ; extra == 'dev'
Requires-Dist: logging-tree ; extra == 'dev'
Requires-Dist: pre-commit ; extra == 'dev'
Requires-Dist: coverage ; extra == 'dev'
Requires-Dist: pep8 ; extra == 'dev'
Requires-Dist: flake8 ; extra == 'dev'
Requires-Dist: flake8-quotes (==0.8.1) ; extra == 'dev'
Requires-Dist: hypothesis (>=5.3.0) ; extra == 'dev'
Requires-Dist: pytest (>=3.0.0) ; extra == 'dev'
Requires-Dist: pytest-cov (>=2.2.1) ; extra == 'dev'
Requires-Dist: pytest-mock ; extra == 'dev'
Requires-Dist: pytest-xdist ; extra == 'dev'
Requires-Dist: pytest-flask ; extra == 'dev'
Requires-Dist: pytest-aiohttp ; extra == 'dev'
Requires-Dist: pytest-asyncio ; extra == 'dev'
Requires-Dist: tox ; extra == 'dev'
Requires-Dist: Sphinx (~=1.0) ; extra == 'dev'
Requires-Dist: recommonmark (>=0.4.0) ; extra == 'dev'
Requires-Dist: sphinx-rtd-theme (>=0.1.9) ; extra == 'dev'
Requires-Dist: sphinxcontrib-httpdomain (>=1.5.0) ; extra == 'dev'
Requires-Dist: sphinxcontrib-napoleon (>=0.4.4) ; extra == 'dev'
Requires-Dist: aafigure (>=0.6) ; extra == 'dev'
Requires-Dist: wget ; extra == 'dev'
Provides-Extra: docs
Requires-Dist: Sphinx (~=1.0) ; extra == 'docs'
Requires-Dist: recommonmark (>=0.4.0) ; extra == 'docs'
Requires-Dist: sphinx-rtd-theme (>=0.1.9) ; extra == 'docs'
Requires-Dist: sphinxcontrib-httpdomain (>=1.5.0) ; extra == 'docs'
Requires-Dist: sphinxcontrib-napoleon (>=0.4.4) ; extra == 'docs'
Requires-Dist: aafigure (>=0.6) ; extra == 'docs'
Requires-Dist: wget ; extra == 'docs'
Provides-Extra: test
Requires-Dist: coverage ; extra == 'test'
Requires-Dist: pep8 ; extra == 'test'
Requires-Dist: flake8 ; extra == 'test'
Requires-Dist: flake8-quotes (==0.8.1) ; extra == 'test'
Requires-Dist: hypothesis (>=5.3.0) ; extra == 'test'
Requires-Dist: pytest (>=3.0.0) ; extra == 'test'
Requires-Dist: pytest-cov (>=2.2.1) ; extra == 'test'
Requires-Dist: pytest-mock ; extra == 'test'
Requires-Dist: pytest-xdist ; extra == 'test'
Requires-Dist: pytest-flask ; extra == 'test'
Requires-Dist: pytest-aiohttp ; extra == 'test'
Requires-Dist: pytest-asyncio ; extra == 'test'
Requires-Dist: tox ; extra == 'test'
Requires-Dist: Sphinx (~=1.0) ; extra == 'test'
Requires-Dist: recommonmark (>=0.4.0) ; extra == 'test'
Requires-Dist: sphinx-rtd-theme (>=0.1.9) ; extra == 'test'
Requires-Dist: sphinxcontrib-httpdomain (>=1.5.0) ; extra == 'test'
Requires-Dist: sphinxcontrib-napoleon (>=0.4.4) ; extra == 'test'
Requires-Dist: aafigure (>=0.6) ; extra == 'test'
Requires-Dist: wget ; extra == 'test'
